{
  "1691588604541.png": {
    "svg": "${appResourceUrl}/images/icon_picker_in_setting/1691588604541.png",
    "properties": {
      "filename": "1691588604541.png",
      "originalName": "Expand.png",
      "path": "${appResourceUrl}/images/icon_picker_in_setting/1691588604541.png",
      "inlineSvg": false
    }
  },
  "1695060108803.png": {
    "svg": "${appResourceUrl}/images/icon_picker_in_setting/1695060108803.png",
    "properties": {
      "filename": "1695060108803.png",
      "originalName": "filter.png",
      "path": "${appResourceUrl}/images/icon_picker_in_setting/1695060108803.png",
      "color": "var(--dark-800)",
      "size": 16,
      "inlineSvg": false,
      "isUploaded": true
    }
  },
  "1695060528101.png": {
    "svg": "${appResourceUrl}/images/icon_picker_in_setting/1695060528101.png",
    "properties": {
      "filename": "1695060528101.png",
      "originalName": "icons8-filter-96.png",
      "path": "${appResourceUrl}/images/icon_picker_in_setting/1695060528101.png",
      "inlineSvg": false
    }
  },
  "1695062389253.png": {
    "svg": "${appResourceUrl}/images/icon_picker_in_setting/1695062389253.png",
    "properties": {
      "filename": "1695062389253.png",
      "originalName": "Print.png",
      "path": "${appResourceUrl}/images/icon_picker_in_setting/1695062389253.png",
      "inlineSvg": false
    }
  },
  "1695062398070.png": {
    "svg": "${appResourceUrl}/images/icon_picker_in_setting/1695062398070.png",
    "properties": {
      "filename": "1695062398070.png",
      "originalName": "Share.png",
      "path": "${appResourceUrl}/images/icon_picker_in_setting/1695062398070.png",
      "inlineSvg": false
    }
  },
  "1695062410644.png": {
    "svg": "${appResourceUrl}/images/icon_picker_in_setting/1695062410644.png",
    "properties": {
      "filename": "1695062410644.png",
      "originalName": "Layers.png",
      "path": "${appResourceUrl}/images/icon_picker_in_setting/1695062410644.png",
      "inlineSvg": false
    }
  },
  "1695062551024.png": {
    "svg": "${appResourceUrl}/images/icon_picker_in_setting/1695062551024.png",
    "properties": {
      "filename": "1695062551024.png",
      "originalName": "Draw.png",
      "path": "${appResourceUrl}/images/icon_picker_in_setting/1695062551024.png",
      "inlineSvg": false
    }
  },
  "1695062574974.png": {
    "svg": "${appResourceUrl}/images/icon_picker_in_setting/1695062574974.png",
    "properties": {
      "filename": "1695062574974.png",
      "originalName": "Add.png",
      "path": "${appResourceUrl}/images/icon_picker_in_setting/1695062574974.png",
      "inlineSvg": false
    }
  },
  "1703000438320.png": {
    "svg": "${appResourceUrl}/images/icon_picker_in_setting/1703000438320.png",
    "properties": {
      "filename": "1703000438320.png",
      "originalName": "icons8-menu-64.png",
      "path": "${appResourceUrl}/images/icon_picker_in_setting/1703000438320.png",
      "color": "var(--dark-800)",
      "size": 16,
      "inlineSvg": false,
      "isUploaded": true
    }
  },
  "1703000445856.png": {
    "svg": "${appResourceUrl}/images/icon_picker_in_setting/1703000445856.png",
    "properties": {
      "filename": "1703000445856.png",
      "originalName": "icons8-menu-128.png",
      "path": "${appResourceUrl}/images/icon_picker_in_setting/1703000445856.png",
      "inlineSvg": false
    }
  },
  "1703006473083.png": {
    "svg": "${appResourceUrl}/images/icon_picker_in_setting/1703006473083.png",
    "properties": {
      "filename": "1703006473083.png",
      "originalName": "Menu.png",
      "path": "${appResourceUrl}/images/icon_picker_in_setting/1703006473083.png",
      "inlineSvg": false
    }
  },
  "1703006714902.png": {
    "svg": "${appResourceUrl}/images/icon_picker_in_setting/1703006714902.png",
    "properties": {
      "filename": "1703006714902.png",
      "originalName": "CgMenuRound.png",
      "path": "${appResourceUrl}/images/icon_picker_in_setting/1703006714902.png",
      "inlineSvg": false
    }
  },
  "1703006857610.png": {
    "svg": "${appResourceUrl}/images/icon_picker_in_setting/1703006857610.png",
    "properties": {
      "filename": "1703006857610.png",
      "originalName": "CgMenuRound (1).png",
      "path": "${appResourceUrl}/images/icon_picker_in_setting/1703006857610.png",
      "inlineSvg": false
    }
  }
}